causal_chains/CausalChain.py
causal_chains/__intit__.py
causal_chains/chainer.py
causal_chains-1.0.12.dist-info/LICENCE
causal_chains-1.0.12.dist-info/METADATA
causal_chains-1.0.12.dist-info/WHEEL
causal_chains-1.0.12.dist-info/top_level.txt
causal_chains-1.0.12.dist-info/RECORD
