Metadata-Version: 2.1
Name: causal-chains
Version: 1.0.12
Summary: A package for extracting causal chains from text
Home-page: https://github.com/helliun/causal-chains
Author: Henry Leonardi
Author-email: leonardi.henry@gmail.com
Classifier: Programming Language :: Python :: 3
Classifier: License :: OSI Approved :: MIT License
Classifier: Operating System :: OS Independent
License-File: LICENCE
Requires-Dist: hatchling
Requires-Dist: transformers
Requires-Dist: sentence-transformers
Requires-Dist: pydot
Requires-Dist: tqdm
